immunity_ipam/__init__.py
immunity_ipam/admin.py
immunity_ipam/apps.py
immunity_ipam/filters.py
immunity_ipam/models.py
immunity_ipam/urls.py
immunity_ipam/api/__init__.py
immunity_ipam/api/responses.py
immunity_ipam/api/serializers.py
immunity_ipam/api/urls.py
immunity_ipam/api/utils.py
immunity_ipam/api/views.py
immunity_ipam/base/__init__.py
immunity_ipam/base/fields.py
immunity_ipam/base/forms.py
immunity_ipam/base/models.py
immunity_ipam/management/__init__.py
immunity_ipam/management/commands/__init__.py
immunity_ipam/management/commands/export_subnet.py
immunity_ipam/management/commands/import_subnet.py
immunity_ipam/migrations/__init__.py
immunity_ipam/static/openwisp-ipam/css/admin.css
immunity_ipam/static/openwisp-ipam/css/minified/32px.png
immunity_ipam/static/openwisp-ipam/css/minified/40px.png
immunity_ipam/static/openwisp-ipam/css/minified/jstree.min.css
immunity_ipam/static/openwisp-ipam/css/minified/throbber.gif
immunity_ipam/static/openwisp-ipam/js/ip-request.js
immunity_ipam/static/openwisp-ipam/js/subnet.js
immunity_ipam/static/openwisp-ipam/js/minified/jstree.min.js
immunity_ipam/static/openwisp-ipam/js/minified/plotly.min.js
immunity_ipam/templates/admin/openwisp-ipam/ip_address/change_form.html
immunity_ipam/templates/admin/openwisp-ipam/subnet/change_form.html
immunity_ipam/templates/admin/openwisp-ipam/subnet/change_list.html
immunity_ipam/templates/admin/openwisp-ipam/subnet/import.html
immunity_ipam/tests/__init__.py
immunity_ipam/tests/test_admin.py
immunity_ipam/tests/test_api.py
immunity_ipam/tests/test_commands.py
immunity_ipam/tests/test_forms.py
immunity_ipam/tests/test_models.py
immunity_ipam/tests/test_multitenant.py
immunity_ipam/tests/test_users_integration.py
immunity_ipam/tests/static/import_data.xlsx
immunity_ipam/tests/static/invalid_data.csv
immunity_ipam-1.1.dist-info/LICENSE
immunity_ipam-1.1.dist-info/METADATA
immunity_ipam-1.1.dist-info/WHEEL
immunity_ipam-1.1.dist-info/top_level.txt
immunity_ipam-1.1.dist-info/RECORD
