Metadata-Version: 2.1
Name: immunity-ipam
Version: 1.1
Summary: IP address space administration module of OpenWISP.
Home-page: https://github.com/edge-servers/immunity-ipam
Author: OpenWISP
Author-email: support@openwisp.io
License: BSD-3-Clause
Download-URL: https://github.com/edge-servers/immunity-ipam/releases
Keywords: django,freeradius,networking,openwisp
Platform: Platform Independent
Classifier: Development Status :: 5 - Production/Stable 
Classifier: Environment :: Web Environment
Classifier: Topic :: Internet :: WWW/HTTP
Classifier: Topic :: System :: Networking
Classifier: Intended Audience :: Developers
Classifier: License :: OSI Approved :: BSD License
Classifier: Operating System :: OS Independent
Classifier: Framework :: Django
Classifier: Programming Language :: Python :: 3
License-File: LICENSE
Requires-Dist: django-reversion~=5.1.0
Requires-Dist: immunity-users~=1.1
Requires-Dist: openpyxl~=3.1.5
Requires-Dist: openwisp-utils[rest]~=1.1.0
